charts/__init__.py
charts/admin.py
charts/apps.py
charts/models.py
charts/tests.py
charts/urls.py
charts/views.py
charts/migrations/__init__.py
Shreya_Dhumal_finance_charts-0.2.dist-info/LICENSE
Shreya_Dhumal_finance_charts-0.2.dist-info/METADATA
Shreya_Dhumal_finance_charts-0.2.dist-info/WHEEL
Shreya_Dhumal_finance_charts-0.2.dist-info/top_level.txt
Shreya_Dhumal_finance_charts-0.2.dist-info/RECORD
